timekeeper.py
timekeeper-0.1.1.dist-info/DESCRIPTION.rst
timekeeper-0.1.1.dist-info/METADATA
timekeeper-0.1.1.dist-info/metadata.json
timekeeper-0.1.1.dist-info/RECORD
timekeeper-0.1.1.dist-info/top_level.txt
timekeeper-0.1.1.dist-info/WHEEL
