Metadata-Version: 2.0
Name: timekeeper
Version: 0.1.1
Summary: Send runtime measurements of your code to InfluxDB
Home-page: https://github.com/trehn/timekeeper
Author: Torsten Rehn
Author-email: torsten@rehn.email
License: ISC
Keywords: profiling,profile,metrics,instrumentation,measure,influxdb
Platform: UNKNOWN
Classifier: Development Status :: 4 - Beta
Classifier: Intended Audience :: Developers
Classifier: License :: OSI Approved :: ISC License (ISCL)
Classifier: Operating System :: MacOS :: MacOS X
Classifier: Operating System :: POSIX
Classifier: Operating System :: Unix
Classifier: Programming Language :: Python :: 2.7
Classifier: Programming Language :: Python :: 3.2
Classifier: Programming Language :: Python :: 3.3
Classifier: Programming Language :: Python :: 3.4
Classifier: Topic :: Software Development :: Libraries :: Python Modules
Classifier: Topic :: System :: Monitoring
Requires-Dist: influxdb (>=2.0.0)
